LICENSE
README.md
setup.py
nanh_easy_google_search/__init__.py
nanh_easy_google_search/example.py
nanh_easy_google_search/google.py
nanh_easy_google_search.egg-info/PKG-INFO
nanh_easy_google_search.egg-info/SOURCES.txt
nanh_easy_google_search.egg-info/dependency_links.txt
nanh_easy_google_search.egg-info/requires.txt
nanh_easy_google_search.egg-info/top_level.txt