Metadata-Version: 2.1
Name: nanh-easy-google-search
Version: 1.0.0
Summary: Google搜索工具
Home-page: https://github.com/877007021/easy_google_search
Author: nanh
Author-email: 877007021@qq.com
License-File: LICENSE
Requires-Dist: beautifulsoup4
Requires-Dist: Requests
Requires-Dist: urllib3
